fmn/__init__.py
fmn/api/__init__.py
fmn/api/api_models.py
fmn/api/auth.py
fmn/api/cli.py
fmn/api/database.py
fmn/api/handlers/__init__.py
fmn/api/handlers/admin.py
fmn/api/handlers/misc.py
fmn/api/handlers/users.py
fmn/api/handlers/utils.py
fmn/api/main.py
fmn/api/messaging.py
fmn/backends/__init__.py
fmn/backends/base.py
fmn/backends/fasjson.py
fmn/backends/pagure.py
fmn/backends/pagure_models.py
fmn/cache/__init__.py
fmn/cache/base.py
fmn/cache/cli.py
fmn/cache/rules.py
fmn/cache/tracked.py
fmn/cache/util.py
fmn/consumer/__init__.py
fmn/consumer/consumer.py
fmn/consumer/send_queue.py
fmn/core/__init__.py
fmn/core/amqp.py
fmn/core/cli.py
fmn/core/collectd.py
fmn/core/config.py
fmn/core/constants.py
fmn/core/version.py
fmn/database/__init__.py
fmn/database/cli.py
fmn/database/main.py
fmn/database/migrations/alembic.ini
fmn/database/migrations/env.py
fmn/database/migrations/script.py.mako
fmn/database/migrations/versions/.empty
fmn/database/migrations/versions/59e22969e199_add_generated_table.py
fmn/database/migrations/versions/7b47f8356d9f_initial_empty_migration.py
fmn/database/migrations/versions/85ea1d6c9a3f_rule_name_is_optional.py
fmn/database/migrations/versions/a6c12ef04ee5_create_rule_disabled.py
fmn/database/model/__init__.py
fmn/database/model/destination.py
fmn/database/model/filter.py
fmn/database/model/generated.py
fmn/database/model/generation_rule.py
fmn/database/model/rule.py
fmn/database/model/tracking_rule.py
fmn/database/model/user.py
fmn/rules/__init__.py
fmn/rules/filter.py
fmn/rules/notification.py
fmn/rules/requester.py
fmn/rules/tracking_rules.py
fmn/sender/__init__.py
fmn/sender/cli.py
fmn/sender/config.py
fmn/sender/consumer.py
fmn/sender/email.py
fmn/sender/handler.py
fmn/sender/irc.py
fmn/sender/matrix.py
fmn-3.4.0.dist-info/METADATA
fmn-3.4.0.dist-info/WHEEL
fmn-3.4.0.dist-info/entry_points.txt
fmn-3.4.0.dist-info/licenses/LICENSES/LicenseRef-Fedora-trademark.txt
fmn-3.4.0.dist-info/licenses/LICENSES/LicenseRef-RedHat-trademark.txt
fmn-3.4.0.dist-info/licenses/LICENSES/MIT.txt
fmn-3.4.0.dist-info/RECORD
